{
    "apple_routes": [
        [
            {
                "lat": 37.5228996,
                "lng": 127.0391436
            },
            {
                "lat": 37.5229105,
                "lng": 127.0391897
            },
            {
                "lat": 37.5216695,
                "lng": 127.039635
            },
            {
                "lat": 37.5215465,
                "lng": 127.0391552
            },
            {
                "lat": 37.5214555,
                "lng": 127.0387758
            },
            {
                "lat": 37.5211672,
                "lng": 127.0375327
            },
            {
                "lat": 37.5208793,
                "lng": 127.0366237
            },
            {
                "lat": 37.5206962,
                "lng": 127.0360147
            },
            {
                "lat": 37.5204469,
                "lng": 127.0351594
            },
            {
                "lat": 37.5204469,
                "lng": 127.0351594
            },
            {
                "lat": 37.5202502,
                "lng": 127.0345263
            },
            {
                "lat": 37.5201906,
                "lng": 127.0343467
            },
            {
                "lat": 37.5196029,
                "lng": 127.0346038
            },
            {
                "lat": 37.5188465,
                "lng": 127.0349318
            },
            {
                "lat": 37.5182746,
                "lng": 127.0351846
            },
            {
                "lat": 37.5181849,
                "lng": 127.0352178
            },
            {
                "lat": 37.5170797,
                "lng": 127.0353171
            },
            {
                "lat": 37.5169804,
                "lng": 127.0344674
            },
            {
                "lat": 37.5169804,
                "lng": 127.0344674
            },
            {
                "lat": 37.5168859,
                "lng": 127.0337525
            },
            {
                "lat": 37.5167696,
                "lng": 127.0332574
            },
            {
                "lat": 37.5167012,
                "lng": 127.0330404
            },
            {
                "lat": 37.5178702,
                "lng": 127.033005
            },
            {
                "lat": 37.5178617,
                "lng": 127.0325668
            },
            {
                "lat": 37.5178573,
                "lng": 127.0324029
            },
            {
                "lat": 37.51785,
                "lng": 127.0321308
            },
            {
                "lat": 37.5178331,
                "lng": 127.0316186
            },
            {
                "lat": 37.5176789,
                "lng": 127.0311067
            },
            {
                "lat": 37.517849,
                "lng": 127.0310233
            },
            {
                "lat": 37.5177584,
                "lng": 127.0303924
            },
            {
                "lat": 37.5179463,
                "lng": 127.0302827
            },
            {
                "lat": 37.5182064,
                "lng": 127.0301019
            },
            {
                "lat": 37.5180895,
                "lng": 127.0297291
            },
            {
                "lat": 37.5180787,
                "lng": 127.0296945
            },
            {
                "lat": 37.5180787,
                "lng": 127.0296945
            },
            {
                "lat": 37.5178759,
                "lng": 127.029092
            },
            {
                "lat": 37.5178514,
                "lng": 127.0290193
            },
            {
                "lat": 37.5170386,
                "lng": 127.0294255
            },
            {
                "lat": 37.5168138,
                "lng": 127.0295416
            },
            {
                "lat": 37.5167888,
                "lng": 127.0293981
            },
            {
                "lat": 37.5167649,
                "lng": 127.0293207
            },
            {
                "lat": 37.5166567,
                "lng": 127.0289696
            },
            {
                "lat": 37.5165524,
                "lng": 127.0286227
            },
            {
                "lat": 37.5163329,
                "lng": 127.0278948
            },
            {
                "lat": 37.5161268,
                "lng": 127.0271888
            },
            {
                "lat": 37.5158602,
                "lng": 127.0268723
            },
            {
                "lat": 37.515797,
                "lng": 127.0267892
            },
            {
                "lat": 37.5155755,
                "lng": 127.0265066
            },
            {
                "lat": 37.5152814,
                "lng": 127.0261461
            },
            {
                "lat": 37.5152814,
                "lng": 127.0261461
            },
            {
                "lat": 37.5148243,
                "lng": 127.0255784
            },
            {
                "lat": 37.5144952,
                "lng": 127.0257364
            },
            {
                "lat": 37.5140064,
                "lng": 127.0259755
            },
            {
                "lat": 37.5134495,
                "lng": 127.0262447
            },
            {
                "lat": 37.5130659,
                "lng": 127.0266309
            },
            {
                "lat": 37.5129031,
                "lng": 127.0267849
            },
            {
                "lat": 37.5128497,
                "lng": 127.0268366
            },
            {
                "lat": 37.5127407,
                "lng": 127.0269464
            },
            {
                "lat": 37.5126968,
                "lng": 127.0269659
            },
            {
                "lat": 37.5122156,
                "lng": 127.0271791
            },
            {
                "lat": 37.5117454,
                "lng": 127.0274131
            },
            {
                "lat": 37.511444,
                "lng": 127.0275573
            },
            {
                "lat": 37.5111426,
                "lng": 127.0280285
            },
            {
                "lat": 37.5103294,
                "lng": 127.0272218
            },
            {
                "lat": 37.5099746,
                "lng": 127.0268644
            },
            {
                "lat": 37.5097873,
                "lng": 127.0266756
            },
            {
                "lat": 37.5097194,
                "lng": 127.0266072
            },
            {
                "lat": 37.5094337,
                "lng": 127.0263194
            },
            {
                "lat": 37.5094337,
                "lng": 127.0263194
            },
            {
                "lat": 37.5089118,
                "lng": 127.026939
            },
            {
                "lat": 37.5084177,
                "lng": 127.0270662
            },
            {
                "lat": 37.5079121,
                "lng": 127.0270716
            },
            {
                "lat": 37.5073943,
                "lng": 127.02711
            },
            {
                "lat": 37.506902,
                "lng": 127.0271492
            },
            {
                "lat": 37.5065043,
                "lng": 127.0273312
            },
            {
                "lat": 37.5060842,
                "lng": 127.0275352
            },
            {
                "lat": 37.5055191,
                "lng": 127.0277835
            },
            {
                "lat": 37.5054321,
                "lng": 127.0278284
            },
            {
                "lat": 37.5055387,
                "lng": 127.0282047
            },
            {
                "lat": 37.505839,
                "lng": 127.0292018
            },
            {
                "lat": 37.5051387,
                "lng": 127.0295473
            },
            {
                "lat": 37.5051497,
                "lng": 127.0296182
            },
            {
                "lat": 37.5054801,
                "lng": 127.0307206
            },
            {
                "lat": 37.5051169,
                "lng": 127.0304434
            },
            {
                "lat": 37.504832,
                "lng": 127.0301957
            },
            {
                "lat": 37.504518,
                "lng": 127.0307463
            },
            {
                "lat": 37.504518,
                "lng": 127.0307463
            },
            {
                "lat": 37.5048183,
                "lng": 127.0310036
            },
            {
                "lat": 37.5046429,
                "lng": 127.031336
            },
            {
                "lat": 37.5042758,
                "lng": 127.031707
            },
            {
                "lat": 37.5037952,
                "lng": 127.0325951
            },
            {
                "lat": 37.5037725,
                "lng": 127.0326456
            },
            {
                "lat": 37.5035132,
                "lng": 127.032747
            },
            {
                "lat": 37.5032076,
                "lng": 127.0328883
            },
            {
                "lat": 37.5033264,
                "lng": 127.0332763
            },
            {
                "lat": 37.5034661,
                "lng": 127.0337318
            },
            {
                "lat": 37.5037225,
                "lng": 127.034624
            },
            {
                "lat": 37.5032214,
                "lng": 127.034856
            },
            {
                "lat": 37.5034744,
                "lng": 127.0357109
            },
            {
                "lat": 37.50361,
                "lng": 127.0361406
            },
            {
                "lat": 37.5037358,
                "lng": 127.0365393
            },
            {
                "lat": 37.5039245,
                "lng": 127.0371121
            },
            {
                "lat": 37.5041298,
                "lng": 127.0378107
            },
            {
                "lat": 37.5046337,
                "lng": 127.0383634
            },
            {
                "lat": 37.5047552,
                "lng": 127.0387207
            },
            {
                "lat": 37.504871,
                "lng": 127.039059
            },
            {
                "lat": 37.504944,
                "lng": 127.0392712
            },
            {
                "lat": 37.5049926,
                "lng": 127.0394009
            },
            {
                "lat": 37.5049926,
                "lng": 127.0394009
            },
            {
                "lat": 37.5051273,
                "lng": 127.0397402
            },
            {
                "lat": 37.5051882,
                "lng": 127.0399169
            },
            {
                "lat": 37.505302,
                "lng": 127.0402331
            },
            {
                "lat": 37.5054122,
                "lng": 127.0405659
            },
            {
                "lat": 37.5058459,
                "lng": 127.0403595
            },
            {
                "lat": 37.5061572,
                "lng": 127.0408521
            },
            {
                "lat": 37.5069441,
                "lng": 127.0401037
            },
            {
                "lat": 37.5069825,
                "lng": 127.0402835
            },
            {
                "lat": 37.5071693,
                "lng": 127.0408977
            },
            {
                "lat": 37.5073196,
                "lng": 127.0414022
            },
            {
                "lat": 37.5073332,
                "lng": 127.0414455
            },
            {
                "lat": 37.5074678,
                "lng": 127.0419012
            },
            {
                "lat": 37.5075359,
                "lng": 127.0421516
            },
            {
                "lat": 37.5076386,
                "lng": 127.0424891
            },
            {
                "lat": 37.5077347,
                "lng": 127.0428247
            },
            {
                "lat": 37.5078056,
                "lng": 127.0430321
            },
            {
                "lat": 37.5079312,
                "lng": 127.0431495
            },
            {
                "lat": 37.5083528,
                "lng": 127.0435432
            },
            {
                "lat": 37.5084708,
                "lng": 127.0434854
            },
            {
                "lat": 37.5086136,
                "lng": 127.0434222
            },
            {
                "lat": 37.5089614,
                "lng": 127.043309
            },
            {
                "lat": 37.5090378,
                "lng": 127.0435589
            },
            {
                "lat": 37.5091001,
                "lng": 127.0437743
            },
            {
                "lat": 37.5091001,
                "lng": 127.0437743
            },
            {
                "lat": 37.5090378,
                "lng": 127.0435589
            },
            {
                "lat": 37.5089614,
                "lng": 127.043309
            },
            {
                "lat": 37.5090703,
                "lng": 127.0427523
            },
            {
                "lat": 37.5098561,
                "lng": 127.0423938
            },
            {
                "lat": 37.5105939,
                "lng": 127.0420664
            },
            {
                "lat": 37.5112341,
                "lng": 127.041826
            },
            {
                "lat": 37.5111393,
                "lng": 127.0413782
            },
            {
                "lat": 37.5110265,
                "lng": 127.0408722
            },
            {
                "lat": 37.5117136,
                "lng": 127.0406269
            },
            {
                "lat": 37.5122084,
                "lng": 127.0404443
            },
            {
                "lat": 37.5124109,
                "lng": 127.0403696
            },
            {
                "lat": 37.5124109,
                "lng": 127.0403696
            },
            {
                "lat": 37.5128507,
                "lng": 127.0402069
            },
            {
                "lat": 37.5130968,
                "lng": 127.0401149
            },
            {
                "lat": 37.5132068,
                "lng": 127.0405633
            },
            {
                "lat": 37.5133163,
                "lng": 127.0410457
            },
            {
                "lat": 37.5134792,
                "lng": 127.0417314
            },
            {
                "lat": 37.5136882,
                "lng": 127.0426222
            },
            {
                "lat": 37.5137999,
                "lng": 127.04307
            },
            {
                "lat": 37.5139007,
                "lng": 127.0434601
            },
            {
                "lat": 37.5153383,
                "lng": 127.0429472
            },
            {
                "lat": 37.5158723,
                "lng": 127.0427625
            },
            {
                "lat": 37.5166837,
                "lng": 127.0424637
            },
            {
                "lat": 37.5166837,
                "lng": 127.0424637
            },
            {
                "lat": 37.5165004,
                "lng": 127.0415543
            },
            {
                "lat": 37.5171092,
                "lng": 127.0413315
            },
            {
                "lat": 37.5172852,
                "lng": 127.0412532
            },
            {
                "lat": 37.5179255,
                "lng": 127.0410421
            },
            {
                "lat": 37.5183659,
                "lng": 127.0408711
            },
            {
                "lat": 37.5182508,
                "lng": 127.0403933
            },
            {
                "lat": 37.5181562,
                "lng": 127.0399946
            },
            {
                "lat": 37.5180661,
                "lng": 127.0396213
            },
            {
                "lat": 37.5180661,
                "lng": 127.0396213
            },
            {
                "lat": 37.5179829,
                "lng": 127.039285
            },
            {
                "lat": 37.5179034,
                "lng": 127.0389347
            },
            {
                "lat": 37.5178091,
                "lng": 127.0385456
            },
            {
                "lat": 37.5175786,
                "lng": 127.0375661
            },
            {
                "lat": 37.5174689,
                "lng": 127.0370616
            },
            {
                "lat": 37.517392,
                "lng": 127.0367693
            },
            {
                "lat": 37.5167235,
                "lng": 127.0366051
            },
            {
                "lat": 37.5166612,
                "lng": 127.03627
            },
            {
                "lat": 37.5165162,
                "lng": 127.0355003
            },
            {
                "lat": 37.5164805,
                "lng": 127.0353241
            },
            {
                "lat": 37.5170797,
                "lng": 127.0353171
            },
            {
                "lat": 37.5170797,
                "lng": 127.0353171
            },
            {
                "lat": 37.5181849,
                "lng": 127.0352178
            },
            {
                "lat": 37.5182206,
                "lng": 127.0354058
            },
            {
                "lat": 37.5183696,
                "lng": 127.036245
            },
            {
                "lat": 37.5185859,
                "lng": 127.0373337
            },
            {
                "lat": 37.5186819,
                "lng": 127.0378701
            },
            {
                "lat": 37.5192758,
                "lng": 127.0378141
            },
            {
                "lat": 37.519844,
                "lng": 127.0377475
            },
            {
                "lat": 37.5200258,
                "lng": 127.0385516
            },
            {
                "lat": 37.5200258,
                "lng": 127.0385516
            },
            {
                "lat": 37.5206655,
                "lng": 127.0383448
            },
            {
                "lat": 37.5208236,
                "lng": 127.0390123
            },
            {
                "lat": 37.5214555,
                "lng": 127.0387758
            },
            {
                "lat": 37.5215465,
                "lng": 127.0391552
            },
            {
                "lat": 37.5216695,
                "lng": 127.039635
            },
            {
                "lat": 37.5229105,
                "lng": 127.0391897
            },
            {
                "lat": 37.5228996,
                "lng": 127.0391436
            }
        ]
    ]
}